fancy/eventbus/LICENSE.txt
fancy/eventbus/README.md
fancy/eventbus/__init__.py
fancy/eventbus/event_bus.py
fancy/eventbus/event_executor.py
fancy/eventbus/event_listener.py
fancy/eventbus/event_loop.py
fancy/eventbus/event_priority.py
fancy/eventbus/event_scheduler.py
fancy/eventbus/functions.py
fancy/eventbus/requirements.txt
fancy/eventbus/subscribe_event.py
fancy/eventbus/events/__init__.py
fancy/eventbus/events/start_event.py
fancy/eventbus/execeptions/__init__.py
fancy/eventbus/execeptions/fancy_event_bus_exception.py
fancy/eventbus/execeptions/stop_looping_exception.py
fancy/eventbus/executor/__init__.py
fancy/eventbus/executor/executor_base.py
fancy/eventbus/executor/main_executor.py
fancy/eventbus/executor/thread_executor.py
fancy/eventbus/scheduler/__init__.py
fancy/eventbus/scheduler/multilevel_feedback_queue_scheduler.py
fancy/eventbus/scheduler/prioritiable.py
fancy/eventbus/scheduler/scheduler_base.py
scripts/inspect_methods.py
scripts/script.py
fancy_eventbus-0.1.0a0.dist-info/METADATA
fancy_eventbus-0.1.0a0.dist-info/WHEEL
fancy_eventbus-0.1.0a0.dist-info/top_level.txt
fancy_eventbus-0.1.0a0.dist-info/RECORD
