Metadata-Version: 2.1
Name: fancy-eventbus
Version: 0.1.0a0
Summary: a event bus
Home-page: UNKNOWN
Author: su-rin
Author-email: susautw@gmail.com
License: MIT
Project-URL: Source Code, https://github.com/susautw/fancy-eventbus
Keywords: event
Platform: UNKNOWN
Classifier: Programming Language :: Python :: 3
Classifier: License :: OSI Approved :: MIT License
Classifier: Operating System :: OS Independent
Requires-Python: >=3.6
Requires-Dist: fancy-descriptor (>=1.2.0a0)
